hicrep/__init__.py
hicrep/__main__.py
hicrep/hicrep.py
hicrep/utils.py
hicrep-0.1.3.dist-info/METADATA
hicrep-0.1.3.dist-info/WHEEL
hicrep-0.1.3.dist-info/entry_points.txt
hicrep-0.1.3.dist-info/top_level.txt
hicrep-0.1.3.dist-info/RECORD
