Metadata-Version: 2.1
Name: hicrep
Version: 0.1.3
Summary: Python implementation of HiCRep stratum-adjusted correlation coefficient of Hi-C data with sparse contact matrix support
Home-page: https://github.com/dejunlin/hicrep.git
Author: Dejun Lin
Author-email: dejun.lin@gmail.com
License: MIT
Platform: UNKNOWN
Classifier: License :: OSI Approved :: MIT License
Classifier: Programming Language :: Python
Classifier: Programming Language :: Python :: 3
Requires-Python: >=3.7.6
Requires-Dist: numpy
Requires-Dist: scipy
Requires-Dist: cooler
Requires-Dist: pandas
Requires-Dist: h5py
Requires-Dist: statsmodels
